oofd_kz_parser/__init__.py
oofd_kz_parser/const.py
oofd_kz_parser/exceptions.py
oofd_kz_parser/models.py
oofd_kz_parser/parser.py
oofd_kz_parser/settings.py
oofd_kz_parser-0.1.1.dist-info/WHEEL
oofd_kz_parser-0.1.1.dist-info/METADATA
oofd_kz_parser-0.1.1.dist-info/RECORD
